{
  "seats": {
    "0": {
      "left": 1082,
      "top": 162,
      "width": 200,
      "height": 214
    },
    "1": {
      "left": 1082,
      "top": 542,
      "width": 200,
      "height": 214
    },
    "2": {
      "left": 776,
      "top": 546,
      "width": 200,
      "height": 214
    },
    "3": {
      "left": 439,
      "top": 549,
      "width": 200,
      "height": 214
    },
    "4": {
      "left": 122,
      "top": 542,
      "width": 200,
      "height": 214
    },
    "5": {
      "left": 122,
      "top": 162,
      "width": 200,
      "height": 214
    }
  },
  "bets": {
    "0": {
      "left": 920,
      "top": 170,
      "width": 60,
      "height": 40
    },
    "1": {
      "left": 944,
      "top": 394,
      "width": 22.015625,
      "height": 14
    },
    "2": {
      "left": 728,
      "top": 408,
      "width": 22.015625,
      "height": 14
    },
    "3": {
      "left": 428,
      "top": 408,
      "width": 22.015625,
      "height": 14
    },
    "4": {
      "left": 284,
      "top": 394,
      "width": 22.015625,
      "height": 14
    },
    "5": {
      "left": 290,
      "top": 160,
      "width": 22.015625,
      "height": 14
    }
  },
  "stacks": {
    "0": {
      "left": 1081,
      "top": 331,
      "width": 113.46875,
      "height": 30
    },
    "1": {
      "left": 1089,
      "top": 689,
      "width": 113.46875,
      "height": 30
    },
    "2": {
      "left": 757,
      "top": 697,
      "width": 113.46875,
      "height": 30
    },
    "3": {
      "left": 430,
      "top": 690,
      "width": 113.46875,
      "height": 30
    },
    "4": {
      "left": 129,
      "top": 690,
      "width": 113.46875,
      "height": 30
    },
    "5": {
      "left": 131,
      "top": 331,
      "width": 113.46875,
      "height": 30
    }
  },
  "board": {
    "left": 324,
    "top": 234,
    "width": 0,
    "height": 0
  },
  "pot": {
    "left": 565,
    "top": 405,
    "width": 62.71875,
    "height": 24
  },
  "controls": {
    "left": 500,
    "top": 10,
    "width": 175,
    "height": 250
  },
  "controlsChildren": {
    "check": {
      "left": 50,
      "top": 25,
      "width": 75,
      "height": 35
    },
    "call": {
      "left": 50,
      "top": 65,
      "width": 75,
      "height": 35
    },
    "fold": {
      "left": 50,
      "top": 105,
      "width": 75,
      "height": 35
    },
    "betBtn": {
      "left": 50,
      "top": 145,
      "width": 75,
      "height": 35
    },
    "raise": {
      "left": 50,
      "top": 185,
      "width": 75,
      "height": 35
    },
    "betLabel": {
      "left": 137.4000244140625,
      "top": 80.60000228881836,
      "width": 16,
      "height": 16.00000762939453
    },
    "betInput": {
      "left": 131,
      "top": 20,
      "width": 44.800048828125,
      "height": 16
    },
    "potSlider": {
      "left": 122.199951171875,
      "top": 130,
      "width": 32,
      "height": 100
    },
    "stackSlider": {
      "left": 156.5999755859375,
      "top": 130,
      "width": 32,
      "height": 100
    },
    "stackLabel": {
      "left": 137.4000244140625,
      "top": 180,
      "width": 64,
      "height": 16
    }
  },
  "controlsBox": {
    "width": 170,
    "height": 190
  }
}